Workbook

Sheet Inputs
A1: Flood-Ready Township: cost inputs
A2: Blue numbers are inputs. Prices are public list prices found on 22 Oct 2026. Rows marked Estimate are our assumptions, not quotes.
A4: Input | B4: Low cost | C4: Base | D4: High cost | E4: Unit | F4: Source
A5: Exchange rate | B5: 4.08 | C5: 4.08 | D5: 4.08 | E5: MYR per USD | F5: 30rates.com USD/MYR spot 15-16 Sep 2026 (4.0825), latest spot rate found: https://30rates.com/usd-to-myr-today-forecast-dollar-to-malaysian-ringgit
A6: Water-level sensors in the pilot | B6: 6 | C6: 8 | D6: 10 | E6: sensors | F6: Roadmap Phase 1: 6 to 10 sensors on the memorandum streets
A7: Sensor price | B7: 90 | C7: 111 | D7: 430 | E7: USD each | F7: Low and Base: Dragino DDS75-LB LoRaWAN ultrasonic distance sensor, US retail USD 90 to 111 (https://mydevices.com/product/dragino-dds75-lb-distance-detection-sensor/, https://embeddedworks.net/product/sens778/). High: Milesight EM500-UDL, USD 430 (https://store.mcci.com/products/milesight-em500-udl-ultrasonic-distance-level-sensor). Order the AS923 band for Malaysia.
A8: Installation per sensor | B8: 300 | C8: 500 | D8: 800 | E8: MYR each | F8: Estimate: mounting bracket and labour; no quote yet
A9: LoRaWAN gateways | B9: 1 | C9: 2 | D9: 2 | E9: gateways | F9: Estimate: gateways needed to cover Bukit Raja Phase 1 and 2
A10: Gateway price | B10: 170 | C10: 340 | D10: 467.5 | E10: USD each | F10: Low: Dragino LPS8N, USD 170 (https://www.robotshop.com/products/lps8n-indoor-lorawan-gateway-915-mhz-north-america; 915 MHz listing, AS923 price not found). Base and High: Milesight UG65, USD 340 to 467.50 (https://store.mcci.com/products/milesight-ug65-semi-industrial-lorawan-gateway)
A11: Gateway mobile data | B11: 0 | C11: 38 | D11: 38 | E11: MYR per gateway per month | F11: Low: gateway on SDP office internet. Base and High: U Mobile unlimited data plan, RM38 per month (https://www.instarem.com/blog/the-best-mobile-plans-malaysia/)
A12: Cloud server | B12: 12 | C12: 12 | D12: 24 | E12: USD per month | F12: DigitalOcean droplet, 2 GB (USD 12) or 4 GB (USD 24) (https://www.vpsbenchmarks.com/hosters/digitalocean/plans/std_2gb_1core)
A13: Sensor upkeep | B13: 100 | C13: 200 | D13: 400 | E13: MYR per sensor per year | F13: Estimate: batteries, cleaning and site visits
A14: Ops staff time | B14: 0.1 | C14: 0.25 | D14: 0.5 | E14: share of one full-time job | F14: Estimate
A15: Ops staff salary | B15: 2500 | C15: 4064 | D15: 6000 | E15: MYR per month | F15: Low: operation executive, Kuala Lumpur average RM2,500 (https://www.ajobthing.com/resources/recruitment-tools/salary-comparison-tool/operation-executive-salary-in-kuala-lumpur). Base: DOSM median monthly salary, Kuala Lumpur, 3Q 2025, RM4,064 (https://stashaway.my/r/average-salary-malaysia). High: top KL offers on the AJobThing page, RM6,000
A16: Employer EPF | B16: 0.13 | C16: 0.13 | D16: 0.12 | E16: share of salary | F16: KWSP employer rate: 13% for wages up to RM5,000, 12% above (https://help.talenox.com/en/articles/2488717-epf-contribution-rate)
... A19: Legal review of warning wording | B19: 5000 | C19: 10000 | D19: 20000 | E19: MYR, one-off | F19: Estimate: no quote yet
A21: Avoided loss if the system had run in 2024 (Bandar Bukit Raja)
A22: Input | B22: Low | C22: Base | D22: High | E22: Unit | F22: Source
A23: Avoided loss, residents and SDP | B23: ='Avoided loss'!B38 -> 18100 | C23: ='Avoided loss'!C38 -> 485000 | D23: ='Avoided loss'!D38 -> 4046600 | E23: MYR per year | F23: Calculated on the Avoided loss tab (row 38): flood loss in 2024 x the share the system would have avoided; every input and source is listed there
A24: Of which SDP's own cost avoided | B24: ='Avoided loss'!B37 -> 10000 | C24: ='Avoided loss'!C37 -> 225000 | D24: ='Avoided loss'!D37 -> 1640000 | E24: MYR per year | F24: Calculated on the Avoided loss tab (row 37): avoided SDP works, sales discounts and complaint handling

Sheet Avoided loss
A1: How the avoided loss is estimated: Bandar Bukit Raja, 2024
A2: Blue numbers are inputs, either from the cited source or our own estimate (marked Estimate). Every other number is a formula. SDP does not publish its flood cost, so most inputs are estimates.
A4: Item | B4: Low | C4: Base | D4: High | E4: Unit | F4: Source or basis
A5: 1. Flood loss in 2024
A6: Homes with water inside, per flood | B6: 50 | C6: 100 | D6: 200 | E6: homes | F6: Anchored on Sinar Harian, 6 Jun 2023: "an estimated 50 to 100 houses affected" in the Meru and Bukit Raja area on 4 Jun 2023 (https://www.sinarharian.com.my/article/262088/berita/semasa/rancangan-tebatan-banjir-di-klang-dilaksana-segera---nik-nazmi)
A7: Floods that entered homes in 2024 | B7: 1 | C7: 2 | D7: 3 | E7: floods | F7: Estimate: FMT reports a flood on 24 Apr 2024 (https://freemalaysiatoday.com/category/nation/2024/05/24/developers-local-councils-need-to-hash-out-flood-issues-say-bandar-bukit-raja-folk); RTM says no homes were entered on 12 Nov 2024; residents say at least 3 floods a year (https://www.sinarharian.com.my/article/666626/edisi/selangor-kl/penduduk-bandar-bukit-raja-hadap-banjir-kilat-tiga-kali-setahun)
A8: Damage per home per flood | B8: 3000 | C8: 8000 | D8: 15000 | E8: MYR | F8: Estimate: home contents, cleaning and minor repairs after a shallow flash flood (up to 0.6 m)
A9: Cars damaged per flood | B9: 10 | C9: 30 | D9: 60 | E9: cars | F9: Estimate: news reports cars stranded in flood water, e.g. Utusan, 28 Nov 2024 (https://www.utusan.com.my/nasional/tragedi/2024/11/meru-kapar-banjir/)
A10: Repair cost per damaged car | B10: 3000 | C10: 6000 | D10: 12000 | E10: MYR | F10: Estimate
A11: Residents' home damage | B11: =B6*B7*B8 -> 150000 | C11: =C6*C7*C8 -> 1600000 | D11: =D6*D7*D8 -> 9000000 | E11: MYR | F11: Homes x floods x damage per home
A12: Residents' car damage | B12: =B9*B7*B10 -> 30000 | C12: =C9*C7*C10 -> 360000 | D12: =D9*D7*D10 -> 2160000 | E12: MYR | F12: Cars x floods x repair cost
A13: Residents' loss | B13: =B11+B12 -> 180000 | C13: =C11+C12 -> 1960000 | D13: =D11+D12 -> 11160000 | E13: MYR
A14: SDP drainage and response works | B14: 1000000 | C14: 3000000 | D14: 8000000 | E14: MYR | F14: Estimate: SDP reports desilting and drainage works at high-risk townships (Integrated Annual Report 2025, p.137) but does not publish the cost
A15: Flood-exposed Bukit Raja home sales | B15: 100000000 | C15: 100000000 | D15: 100000000 | E15: MYR per year | F15: Estimate: SDP does not publish sales by street
A16: Price discount on those sales | B16: 0 | C16: 0.01 | D16: 0.03 | E16: share of sales | F16: Estimate
A17: SDP sales discounts | B17: =B15*B16 -> 0 | C17: =C15*C16 -> 1000000 | D17: =D15*D16 -> 3000000 | E17: MYR | F17: Sales x discount
A18: SDP complaint handling and staff time | B18: 100000 | C18: 300000 | D18: 600000 | E18: MYR | F18: Estimate
A19: SDP's cost | B19: =B14+B17+B18 -> 1100000 | C19: =C14+C17+C18 -> 4300000 | D19: =D14+D17+D18 -> 11600000 | E19: MYR | F19: Works + sales discounts + complaint handling
A20: Total flood loss, residents and SDP | B20: =B13+B19 -> 1280000 | C20: =C13+C19 -> 6260000 | D20: =D13+D19 -> 22760000 | E20: MYR
A21: SDP profit after tax and minorities (PATAMI), FY2024 | B21: 502200000 | C21: 502200000 | D21: 502200000 | E21: MYR | F21: SDP AGM presentation, 10 Jun 2026, p.19
A22: SDP's cost as a share of FY2024 profit | B22: =IF(B21=0,0,B19/B21) -> 0.0021903624 | C22: =IF(C21=0,0,C19/C21) -> 0.0085623258 | D22: =IF(D21=0,0,D19/D21) -> 0.023098367 | E22: share
A24: 2. What the system would have avoided
A25: Households that get the alert in time and act | B25: 0.3 | C25: 0.5 | D25: 0.7 | E25: share of households | F25: Estimate: how many residents subscribe and act
A26: Home damage cut for households that act | B26: 0.1 | C26: 0.19 | D26: 0.19 | E26: share | F26: Kreibich, Hudson and Merz (EGU 2022): in 4,468 German flood damage cases, warnings at least 1 h ahead cut the contents damage ratio by 4 points from a mean of 21%, about 19% (https://meetingorganizer.copernicus.org/EGU22/EGU22-7247.html). Low case: some warnings come less than 1 h ahead
A27: Car damage cut for households that act | B27: 0.4 | C27: 0.6 | D27: 0.8 | E27: share | F27: Estimate: moving a car to higher ground is the easiest action
A28: SDP works aimed better with street flood records | B28: 0 | C28: 0.05 | D28: 0.1 | E28: share of works | F28: Estimate
A29: Sales discounts avoided | B29: 0 | C29: 0 | D29: 0.2 | E29: share | F29: Estimate: counted in the high case only
A30: Complaint handling saved | B30: 0.1 | C30: 0.25 | D30: 0.4 | E30: share | F30: Estimate
A31: Avoided home damage | B31: =B11*B25*B26 -> 4500 | C31: =C11*C25*C26 -> 152000 | D31: =D11*D25*D26 -> 1197000 | E31: MYR | F31: Home damage x households that act x damage cut
A32: Avoided car damage | B32: =B12*B25*B27 -> 3600 | C32: =C12*C25*C27 -> 108000 | D32: =D12*D25*D27 -> 1209600 | E32: MYR | F32: Car damage x households that act x damage cut
A33: Avoided SDP works | B33: =B14*B28 -> 0 | C33: =C14*C28 -> 150000 | D33: =D14*D28 -> 800000 | E33: MYR
A34: Avoided sales discounts | B34: =B17*B29 -> 0 | C34: =C17*C29 -> 0 | D34: =D17*D29 -> 600000 | E34: MYR
A35: Avoided complaint handling | B35: =B18*B30 -> 10000 | C35: =C18*C30 -> 75000 | D35: =D18*D30 -> 240000 | E35: MYR
A36: Avoided loss, residents | B36: =B31+B32 -> 8100 | C36: =C31+C32 -> 260000 | D36: =D31+D32 -> 2406600 | E36: MYR
A37: Avoided loss, SDP's own cost | B37: =B33+B34+B35 -> 10000 | C37: =C33+C34+C35 -> 225000 | D37: =D33+D34+D35 -> 1640000 | E37: MYR
A38: Avoided loss, residents and SDP | B38: =B36+B37 -> 18100 | C38: =C36+C37 -> 485000 | D38: =D36+D37 -> 4046600 | E38: MYR
A39: Share of the total flood loss avoided | B39: =IF(B20=0,0,B38/B20) -> 0.014140625 | C39: =IF(C20=0,0,C38/C20) -> 0.077476038 | D39: =IF(D20=0,0,D38/D20) -> 0.17779438 | E39: share

Sheet Budget
A1: Bukit Raja pilot (year 1) and yearly cost per township, MYR
A2: All figures are formulas over the Inputs tab.
B3: Low cost | C3: Base | D3: High cost | E3: How it is calculated
A4: One-off equipment and set-up
A5: Water-level sensors | B5: =Inputs!B6*Inputs!B7*Inputs!B5 -> 2203.2 | C5: =Inputs!C6*Inputs!C7*Inputs!C5 -> 3623.04 | D5: =Inputs!D6*Inputs!D7*Inputs!D5 -> 17544 | E5: Sensors x price (USD) x exchange rate
A6: Installation | B6: =Inputs!B6*Inputs!B8 -> 1800 | C6: =Inputs!C6*Inputs!C8 -> 4000 | D6: =Inputs!D6*Inputs!D8 -> 8000 | E6: Sensors x installation per sensor
A7: LoRaWAN gateways | B7: =Inputs!B9*Inputs!B10*Inputs!B5 -> 693.6 | C7: =Inputs!C9*Inputs!C10*Inputs!C5 -> 2774.4 | D7: =Inputs!D9*Inputs!D10*Inputs!D5 -> 3814.8 | E7: Gateways x price (USD) x exchange rate
A8: Legal review of warning wording | B8: =Inputs!B19 -> 5000 | C8: =Inputs!C19 -> 10000 | D8: =Inputs!D19 -> 20000 | E8: One-off
A9: One-off total | B9: =SUM(B5:B8) -> 9696.8 | C9: =SUM(C5:C8) -> 20397.44 | D9: =SUM(D5:D8) -> 49358.8
A11: Running cost per year
A12: Cloud server | B12: =Inputs!B12*12*Inputs!B5 -> 587.52 | C12: =Inputs!C12*12*Inputs!C5 -> 587.52 | D12: =Inputs!D12*12*Inputs!D5 -> 1175.04 | E12: USD per month x 12 x exchange rate
A13: Gateway mobile data | B13: =Inputs!B9*Inputs!B11*12 -> 0 | C13: =Inputs!C9*Inputs!C11*12 -> 912 | D13: =Inputs!D9*Inputs!D11*12 -> 912 | E13: Gateways x plan per month x 12
A14: Sensor upkeep | B14: =Inputs!B6*Inputs!B13 -> 600 | C14: =Inputs!C6*Inputs!C13 -> 1600 | D14: =Inputs!D6*Inputs!D13 -> 4000 | E14: Sensors x upkeep per sensor
A15: Ops staff | B15: =Inputs!B15*(1+Inputs!B16+Inputs!B17)*12*Inputs!B14 -> 3442.5 | C15: =Inputs!C15*(1+Inputs!C16+Inputs!C17)*12*Inputs!C14 -> 13990.32 | D15: =Inputs!D15*(1+Inputs!D16+Inputs!D17)*12*Inputs!D14 -> 40950 | E15: Salary x (1 + EPF + SOCSO) x 12 x share of a full-time job
A16: Running total per year | B16: =SUM(B12:B15) -> 4630.02 | C16: =SUM(C12:C15) -> 17089.84 | D16: =SUM(D12:D15) -> 47037.04
A18: Pilot, year 1 total | B18: =B9+B16 -> 14326.82 | C18: =C9+C16 -> 37487.28 | D18: =D9+D16 -> 96395.84 | E18: One-off total + one year of running cost
A20: Cost per township per year, after the pilot
A21: Equipment spread over its life | B21: =(B5+B6+B7)/Inputs!B18 -> 1174.2 | C21: =(C5+C6+C7)/Inputs!C18 -> 2599.36 | D21: =(D5+D6+D7)/Inputs!D18 -> 7339.7 | E21: (Sensors + installation + gateways) / equipment life
A22: Running cost | B22: =B16 -> 4630.02 | C22: =C16 -> 17089.84 | D22: =D16 -> 47037.04 | E22: Same as the pilot's running cost
A23: Total per township per year | B23: =B21+B22 -> 5804.22 | C23: =C21+C22 -> 19689.2 | D23: =D21+D22 -> 54376.74 | E23: Legal review is one-off, so it is left out

Sheet Cost vs value
A1: SDP's own avoided loss against the yearly running cost of one township, MYR
A2: Above 1.0, SDP saves more each year than the system costs to run.
A4: Avoided-loss scenario | B4: Avoided loss, residents and SDP | C4: SDP's own cost avoided | D4: Cost per township (base) | E4: Cost per township (high cost) | F4: SDP saving per RM1 (base cost) | G4: SDP saving per RM1 (high cost) | H4: Pays back at base cost?
A5: Low | B5: =Inputs!B23 -> 18100 | C5: =Inputs!B24 -> 10000 | D5: =Budget!$C$23 -> 19689.2 | E5: =Budget!$D$23 -> 54376.74 | F5: =IF(D5=0,0,C5/D5) -> 0.50789265 | G5: =IF(E5=0,0,C5/E5) -> 0.18390216 | H5: =IF(F5>=1,"Yes","No") -> No
A6: Base | B6: =Inputs!C23 -> 485000 | C6: =Inputs!C24 -> 225000 | D6: =Budget!$C$23 -> 19689.2 | E6: =Budget!$D$23 -> 54376.74 | F6: =IF(D6=0,0,C6/D6) -> 11.427585 | G6: =IF(E6=0,0,C6/E6) -> 4.1377986 | H6: =IF(F6>=1,"Yes","No") -> Yes
A7: High | B7: =Inputs!D23 -> 4046600 | C7: =Inputs!D24 -> 1640000 | D7: =Budget!$C$23 -> 19689.2 | E7: =Budget!$D$23 -> 54376.74 | F7: =IF(D7=0,0,C7/D7) -> 83.294395 | G7: =IF(E7=0,0,C7/E7) -> 30.159954 | H7: =IF(F7>=1,"Yes","No") -> Yes
A9: The avoided-loss figures are worked out step by step on the Avoided loss tab; most of its inputs are estimates because SDP does not publish its flood cost. In the low case the system does not pay back.
